
{"characteristics":{
    "products":[
        {
    "name":"t7in",
    "id":"1",
    "price": 12,
    "category":"food",
    "availablity":["morocco", "paris"],
    "provider":{
        "adresse":"12/12/12",
        "company name":"7azo9"
            }
        },
    {
    "name":"sokar",
    "id":"2",
    "price": 11,
    "category":"food",
    "availablity":["morocco", "paris"],
    "provider":{
        "adresse":"12/12/12",
        "company name":"7azo9"
            }
        },
    {
    "name":"zit",
    "id":"3",
    "price": 4,
    "category":"food",
    "availablity":["morocco", "paris"],
    "provider":{
        "adresse":"12/12/12",
        "company name":"7azo9"
            }
        },
    {
    "name":"lobia",
    "id":"4",
    "price": 5,
    "category":"food",
    "availablity":["morocco", "paris"],
    "provider":{
        "adresse":"12/12/12",
        "company name":"7azo9"
            }
        }
    ]
 }
}
    




    

